CHANGELOG.md
README.md
myprj/__main__.py
myprj/__version__.py
myprj/cli.py
python_project_poetry_template-0.14.0.dist-info/entry_points.txt
python_project_poetry_template-0.14.0.dist-info/WHEEL
python_project_poetry_template-0.14.0.dist-info/METADATA
python_project_poetry_template-0.14.0.dist-info/RECORD
