Metadata-Version: 2.1
Name: python-project-poetry-template
Version: 0.14.0
Summary: Python Project Poetry Template
Home-page: https://mrjk.github.io/python-project-poetry-template/
License: GPLv3
Keywords: test,lab,template,poetry
Author: mrjk
Requires-Python: >=3.9,<4.0
Classifier: Environment :: Console
Classifier: Framework :: Flake8
Classifier: License :: Other/Proprietary License
Classifier: Operating System :: OS Independent
Classifier: Programming Language :: Python :: 3
Classifier: Programming Language :: Python :: 3.9
Classifier: Programming Language :: Python :: 3.10
Classifier: Programming Language :: Python :: 3.11
Classifier: Topic :: Software Development :: Documentation
Classifier: Topic :: Software Development :: Libraries :: Python Modules
Classifier: Topic :: Software Development :: Quality Assurance
Project-URL: Repository, https://github.com/mrjk/python-project-poetry-template
